easy_boto3/__init__.py
easy_boto3/cloudwatch/__init__.py
easy_boto3/cloudwatch/cloudwatch.py
easy_boto3/cloudwatch/create.py
easy_boto3/cloudwatch/delete.py
easy_boto3/cloudwatch/list.py
easy_boto3/compound.py
easy_boto3/ec2/__init__.py
easy_boto3/ec2/config_parser.py
easy_boto3/ec2/connect.py
easy_boto3/ec2/create.py
easy_boto3/ec2/ec2.py
easy_boto3/ec2/ec2_connections_management.py
easy_boto3/ec2/ec2_instance_management.py
easy_boto3/ec2/list.py
easy_boto3/ec2/logs.py
easy_boto3/ec2/script.py
easy_boto3/ec2/ssh.py
easy_boto3/ec2/start.py
easy_boto3/ec2/stop.py
easy_boto3/ec2/stop_all.py
easy_boto3/ec2/terminate.py
easy_boto3/main.py
easy_boto3/profile/__init__.py
easy_boto3/profile/active.py
easy_boto3/profile/ownership.py
easy_boto3/profile/profile.py
easy_boto3/profile/validation.py
easy_boto3/router.py
easy_boto3/setup_session.py
easy_boto3/utilities/__init__.py
easy_boto3/utilities/aws_profile_parser.py
easy_boto3/utilities/decorators.py
easy_boto3/utilities/logger_maker.py
easy_boto3-0.1.7.dist-info/LICENSE
easy_boto3-0.1.7.dist-info/METADATA
easy_boto3-0.1.7.dist-info/WHEEL
easy_boto3-0.1.7.dist-info/entry_points.txt
easy_boto3-0.1.7.dist-info/RECORD
