Metadata-Version: 2.1
Name: easy-boto3
Version: 0.1.7
Summary: `easy_boto3` simplifies `boto3` usage by adding a command line interface (CLI) and abridged Python API that allows you to easily create, manage, and tear-down AWS resources using `boto3` and `awscli` in a simple, easy to use, and easy to refactor `.yaml` configuration file.
Home-page: https://github.com/jermwatt/easy_boto3
Author: Jeremy Watt
Author-email: jermwatt@gmail.com
Requires-Python: >=3.9,<4.0
Classifier: Programming Language :: Python :: 3
Classifier: Programming Language :: Python :: 3.9
Classifier: Programming Language :: Python :: 3.10
Classifier: Programming Language :: Python :: 3.11
Requires-Dist: boto3 (>=1.26.142,<2.0.0)
Requires-Dist: botocore (>=1.31.1,<2.0.0)
Requires-Dist: fire (>=0.5.0,<0.6.0)
Requires-Dist: paramiko (>=3.2.0,<4.0.0)
Requires-Dist: python-dotenv (>=1.0.0,<2.0.0)
Requires-Dist: pyyaml (>=6.0,<7.0)
Requires-Dist: requests (>=2.31.0,<3.0.0)
Requires-Dist: sshconf (>=0.2.5,<0.3.0)
Requires-Dist: toml (>=0.10.2,<0.11.0)
Requires-Dist: tomli (>=2.0.1,<3.0.0)
Requires-Dist: yaspin (>=2.3.0,<3.0.0)
